meetscribe/__init__.py
meetscribe/core.py
meetscribe/main.py
meetscribe-0.1.4.dist-info/LICENCE
meetscribe-0.1.4.dist-info/METADATA
meetscribe-0.1.4.dist-info/WHEEL
meetscribe-0.1.4.dist-info/entry_points.txt
meetscribe-0.1.4.dist-info/top_level.txt
meetscribe-0.1.4.dist-info/RECORD
