Metadata-Version: 2.2
Name: meetscribe
Version: 0.1.4
Summary: An intelligent audio-to-transcript chatbot powered by Whisper, PyAnnote, FAISS, and LLMs.
Home-page: https://github.com/jagadale1234/meetscribe
Author: Anish Bipin Jagadale
Author-email: jagdaleanish@gmail.com
Classifier: Programming Language :: Python :: 3
Classifier: Operating System :: OS Independent
Classifier: License :: OSI Approved :: MIT License
Requires-Python: >=3.10
License-File: LICENCE
Requires-Dist: streamlit
Requires-Dist: openai-whisper
Requires-Dist: torch
Requires-Dist: torchaudio
Requires-Dist: pyannote.audio
Requires-Dist: faiss-cpu
Requires-Dist: langchain
Requires-Dist: langchain-community
Requires-Dist: langchain-openai
Requires-Dist: transformers[torch]
Requires-Dist: sentence-transformers
Requires-Dist: llama-index
Requires-Dist: numpy<2.0
Dynamic: author
Dynamic: author-email
Dynamic: classifier
Dynamic: description
Dynamic: description-content-type
Dynamic: home-page
Dynamic: requires-dist
Dynamic: requires-python
Dynamic: summary
